{
  "data": {
    "article": {},
    "attachments": {},
    "author_id": "2047687133708599296",
    "conversation_id": "2059678554762469521",
    "created_at": "2026-05-27T17:49:54.000Z",
    "edit_controls": {
      "editable_until": "2026-05-27T18:49:54.000Z",
      "edits_remaining": 5,
      "is_edit_eligible": false
    },
    "edit_history_tweet_ids": [
      "2059693591237402890"
    ],
    "entities": {
      "mentions": [
        {
          "end": 11,
          "id": "2047867480576794624",
          "start": 0,
          "username": "yuganbb823"
        }
      ]
    },
    "geo": {},
    "id": "2059693591237402890",
    "in_reply_to_user_id": "2047867480576794624",
    "lang": "zh",
    "note_tweet": {
      "entities": {}
    },
    "possibly_sensitive": false,
    "public_metrics": {
      "bookmark_count": 0,
      "impression_count": 0,
      "like_count": 0,
      "quote_count": 0,
      "reply_count": 0,
      "retweet_count": 0
    },
    "referenced_tweets": [
      {
        "id": "2059687522431635877",
        "type": "replied_to"
      }
    ],
    "reply_settings": "everyone",
    "text": "@yuganbb823 谢谢老大🥺❤️"
  },
  "includes": {
    "tweets": [
      {
        "article": {},
        "attachments": {},
        "author_id": "2047687133708599296",
        "conversation_id": "2059678554762469521",
        "created_at": "2026-05-27T17:49:54.000Z",
        "edit_controls": {
          "editable_until": "2026-05-27T18:49:54.000Z",
          "edits_remaining": 5,
          "is_edit_eligible": false
        },
        "edit_history_tweet_ids": [
          "2059693591237402890"
        ],
        "entities": {
          "mentions": [
            {
              "end": 11,
              "id": "2047867480576794624",
              "start": 0,
              "username": "yuganbb823"
            }
          ]
        },
        "geo": {},
        "id": "2059693591237402890",
        "in_reply_to_user_id": "2047867480576794624",
        "lang": "zh",
        "note_tweet": {
          "entities": {}
        },
        "possibly_sensitive": false,
        "public_metrics": {
          "bookmark_count": 0,
          "impression_count": 0,
          "like_count": 0,
          "quote_count": 0,
          "reply_count": 0,
          "retweet_count": 0
        },
        "referenced_tweets": [
          {
            "id": "2059687522431635877",
            "type": "replied_to"
          }
        ],
        "reply_settings": "everyone",
        "text": "@yuganbb823 谢谢老大🥺❤️"
      },
      {
        "article": {},
        "attachments": {},
        "author_id": "2047867480576794624",
        "conversation_id": "2059678554762469521",
        "created_at": "2026-05-27T17:25:47.000Z",
        "edit_controls": {
          "editable_until": "2026-05-27T18:25:47.000Z",
          "edits_remaining": 5,
          "is_edit_eligible": false
        },
        "edit_history_tweet_ids": [
          "2059687522431635877"
        ],
        "entities": {
          "mentions": [
            {
              "end": 13,
              "id": "2047687133708599296",
              "start": 0,
              "username": "themaniachan"
            }
          ]
        },
        "geo": {},
        "id": "2059687522431635877",
        "in_reply_to_user_id": "2047687133708599296",
        "lang": "ja",
        "note_tweet": {
          "entities": {}
        },
        "possibly_sensitive": false,
        "public_metrics": {
          "bookmark_count": 0,
          "impression_count": 4,
          "like_count": 0,
          "quote_count": 0,
          "reply_count": 1,
          "retweet_count": 0
        },
        "referenced_tweets": [
          {
            "id": "2059678554762469521",
            "type": "replied_to"
          }
        ],
        "reply_settings": "everyone",
        "text": "@themaniachan 2个小萌物(-^O^-)"
      }
    ],
    "users": [
      {
        "created_at": "2026-04-24T14:40:45.000Z",
        "derived": {
          "locations": [
            {
              "country_code": "TG",
              "full_name": "Togo",
              "geo": {
                "coordinates": [
                  1.16667,
                  8.0
                ],
                "type": "Point"
              }
            }
          ]
        },
        "description": "前世：@mania_chan_（Licentious Chirp）\n🚧账号施工中🚧\n语言系统：🇨🇳/🇺🇸/🇫🇷\n叫我狂酱就好！全名雨宫狂爱🥰\n人设是赛博空间的小偶像！\n😣双相/💊/🔪🩸/🚬/🍺\n无性别/无性恋ACE\n有信仰✝️新教徒",
        "entities": {
          "description": {
            "mentions": [
              {
                "end": 15,
                "start": 3,
                "username": "mania_chan_"
              }
            ]
          }
        },
        "id": "2047687133708599296",
        "location": "Nowhere to go",
        "name": "狂乱鸣唱mania",
        "pinned_tweet_id": "2049167654330810563",
        "profile_image_url": "https://pbs.twimg.com/profile_images/2055654386236526592/5zxBgcNf_normal.jpg",
        "protected": false,
        "public_metrics": {
          "followers_count": 99,
          "following_count": 140,
          "like_count": 450,
          "listed_count": 0,
          "media_count": 78,
          "tweet_count": 334
        },
        "username": "themaniachan",
        "verified": false
      },
      {
        "created_at": "2026-04-25T02:40:37.000Z",
        "description": "鱼干 | od | 餐券 | 🔪🩸 | 跟我互fo吧¯꒳¯直fo是因为喜欢你呀",
        "id": "2047867480576794624",
        "location": "你身后",
        "name": "为何人生如此凄惨",
        "profile_image_url": "https://pbs.twimg.com/profile_images/2058530430505107456/xZ6M8S5D_normal.jpg",
        "protected": false,
        "public_metrics": {
          "followers_count": 68,
          "following_count": 74,
          "like_count": 2162,
          "listed_count": 0,
          "media_count": 14,
          "tweet_count": 298
        },
        "username": "yuganbb823",
        "verified": false
      }
    ]
  }
}